LICENSE
MANIFEST.in
README.rst
requirements.txt
setup.py
comenu/__init__.py
comenu/__main__.py
comenu/comenu.py
comenu.egg-info/PKG-INFO
comenu.egg-info/SOURCES.txt
comenu.egg-info/dependency_links.txt
comenu.egg-info/entry_points.txt
comenu.egg-info/requires.txt
comenu.egg-info/top_level.txt