Metadata-Version: 1.1
Name: comenu
Version: 1.1
Summary: Command line menu and helper utility
Home-page: https://github.com/dmirubtsov/comenu
Author: Dmitry Rubtsov
Author-email: dmitry@rubtsov.eu
License: MIT
Platform: UNKNOWN
Classifier: Environment :: Console
Classifier: Intended Audience :: Developers
Classifier: Natural Language :: English
Classifier: License :: OSI Approved :: MIT License
Classifier: Programming Language :: Python :: 3
